bpemb/__init__.py
bpemb/available_languages.py
bpemb/available_vocab_sizes.py
bpemb/bpemb.py
bpemb/util.py
bpemb-0.3.6.dist-info/LICENSE
bpemb-0.3.6.dist-info/METADATA
bpemb-0.3.6.dist-info/WHEEL
bpemb-0.3.6.dist-info/top_level.txt
bpemb-0.3.6.dist-info/zip-safe
bpemb-0.3.6.dist-info/RECORD
