Metadata-Version: 2.1
Name: bpemb
Version: 0.3.6
Summary: Byte-pair embeddings in 275 languages
Home-page: https://nlp.h-its.org/bpemb
Author: Benjamin Heinzerling
Author-email: benjamin.heinzerling@h-its.org
License: MIT
Classifier: License :: OSI Approved :: MIT License
Classifier: Operating System :: OS Independent
Classifier: Programming Language :: Python :: 3
License-File: LICENSE
